mkdocs_video2_plugin/__init__.py
mkdocs_video2_plugin/plugin.py
mkdocs_video2_plugin/test_plugin.py
mkdocs_video2_plugin-0.0.1.dist-info/licenses/LICENSE
mkdocs_video2_plugin-0.0.1.dist-info/METADATA
mkdocs_video2_plugin-0.0.1.dist-info/WHEEL
mkdocs_video2_plugin-0.0.1.dist-info/entry_points.txt
mkdocs_video2_plugin-0.0.1.dist-info/top_level.txt
mkdocs_video2_plugin-0.0.1.dist-info/RECORD
